{
    "wotd": {
        "number": 4755,
        "lemma": "\u03c3\u03c4\u03c1\u03b1\u03c4\u03b7\u03b3\u1f79\u03c2",
        "xlit": "strat\u0113g\u00f3s",
        "pronunciation": "strat-ay-gos'",
        "description": " a general, i.e. (by implication\n or analogy) a (military) governor (pr\u00e6tor), the chief (pr\u00e6fect) of\n the (Levitical) temple-wardens",
        "kjv_def": "captain, magistrate.",
        "pspeech": "N-DMP"
    },
    "verses": [
        {
            "verse_no": 27024,
            "verse_ref": "Acts 4:1",
            "verse_data": [
                {
                    "BSB Version": " While ",
                    "Str Grk": 1161.0,
                    "lemma": "\u03b4\u1f72",
                    "xlit": "de"
                },
                {
                    "BSB Version": " [Peter and John] ",
                    "Str Grk": 846.0,
                    "lemma": "\u03b1\u1f50\u03c4\u1ff6\u03bd",
                    "xlit": "aut\u014dn"
                },
                {
                    "BSB Version": " were speaking ",
                    "Str Grk": 2980.0,
                    "lemma": "\u039b\u03b1\u03bb\u03bf\u03cd\u03bd\u03c4\u03c9\u03bd",
                    "xlit": "Lalount\u014dn"
                },
                {
                    "BSB Version": " to ",
                    "Str Grk": 4314.0,
                    "lemma": "\u03c0\u03c1\u1f78\u03c2",
                    "xlit": "pros"
                },
                {
                    "BSB Version": " the ",
                    "Str Grk": 3588.0,
                    "lemma": "\u03c4\u1f78\u03bd",
                    "xlit": "ton"
                },
                {
                    "BSB Version": " people ",
                    "Str Grk": 2992.0,
                    "lemma": "\u03bb\u03b1\u1f78\u03bd",
                    "xlit": "laon"
                },
                {
                    "BSB Version": " the ",
                    "Str Grk": 3588.0,
                    "lemma": "\u03bf\u1f31",
                    "xlit": "hoi"
                },
                {
                    "BSB Version": " priests ",
                    "Str Grk": 2409.0,
                    "lemma": "\u1f31\u03b5\u03c1\u03b5\u1fd6\u03c2",
                    "xlit": "hiereis"
                },
                {
                    "BSB Version": " and ",
                    "Str Grk": 2532.0,
                    "lemma": "\u03ba\u03b1\u1f76",
                    "xlit": "kai"
                },
                {
                    "BSB Version": " the ",
                    "Str Grk": 3588.0,
                    "lemma": "\u1f41",
                    "xlit": "ho"
                },
                {
                    "BSB Version": " captain ",
                    "Str Grk": 4755.0,
                    "lemma": "\u03c3\u03c4\u03c1\u03b1\u03c4\u03b7\u03b3\u1f78\u03c2",
                    "xlit": "strat\u0113gos"
                },
                {
                    "BSB Version": " of the ",
                    "Str Grk": 3588.0,
                    "lemma": "\u03c4\u03bf\u1fe6",
                    "xlit": "tou"
                },
                {
                    "BSB Version": " temple guard ",
                    "Str Grk": 2411.0,
                    "lemma": "\u1f31\u03b5\u03c1\u03bf\u1fe6",
                    "xlit": "hierou"
                },
                {
                    "BSB Version": " and ",
                    "Str Grk": 2532.0,
                    "lemma": "\u03ba\u03b1\u1f76",
                    "xlit": "kai"
                },
                {
                    "BSB Version": " the ",
                    "Str Grk": 3588.0,
                    "lemma": "\u03bf\u1f31",
                    "xlit": "hoi"
                },
                {
                    "BSB Version": " Sadducees ",
                    "Str Grk": 4523.0,
                    "lemma": "\u03a3\u03b1\u03b4\u03b4\u03bf\u03c5\u03ba\u03b1\u1fd6\u03bf\u03b9",
                    "xlit": "Saddoukaioi"
                },
                {
                    "BSB Version": " came ",
                    "Str Grk": 2186.0,
                    "lemma": "\u1f10\u03c0\u03ad\u03c3\u03c4\u03b7\u03c3\u03b1\u03bd",
                    "xlit": "epest\u0113san"
                },
                {
                    "BSB Version": " up to them ",
                    "Str Grk": 846.0,
                    "lemma": "\u03b1\u1f50\u03c4\u03bf\u1fd6\u03c2",
                    "xlit": "autois"
                }
            ],
            "verse_text": "And of them speaking to the people, the priests and the captain of the temple and the Sadducees came upon them,"
        },
        {
            "verse_no": 25917,
            "verse_ref": "Luke 22:52",
            "verse_data": [
                {
                    "BSB Version": " Then ",
                    "Str Grk": 1161.0,
                    "lemma": "\u03b4\u1f72",
                    "xlit": "de"
                },
                {
                    "BSB Version": " Jesus ",
                    "Str Grk": 2424.0,
                    "lemma": "\u1f38\u03b7\u03c3\u03bf\u1fe6\u03c2",
                    "xlit": "I\u0113sous"
                },
                {
                    "BSB Version": " said ",
                    "Str Grk": 2036.0,
                    "lemma": "\u0395\u1f36\u03c0\u03b5\u03bd",
                    "xlit": "Eipen"
                },
                {
                    "BSB Version": " to ",
                    "Str Grk": 4314.0,
                    "lemma": "\u03c0\u03c1\u1f78\u03c2",
                    "xlit": "pros"
                },
                {
                    "BSB Version": " [the] chief priests ",
                    "Str Grk": 749.0,
                    "lemma": "\u1f00\u03c1\u03c7\u03b9\u03b5\u03c1\u03b5\u1fd6\u03c2",
                    "xlit": "archiereis"
                },
                {
                    "BSB Version": " - ",
                    "Str Grk": 2532.0,
                    "lemma": "\u03ba\u03b1\u1f76",
                    "xlit": "kai"
                },
                {
                    "BSB Version": " temple officers ",
                    "Str Grk": 4755.0,
                    "lemma": "\u03c3\u03c4\u03c1\u03b1\u03c4\u03b7\u03b3\u03bf\u1f7a\u03c2",
                    "xlit": "strat\u0113gous"
                },
                {
                    "BSB Version": " . . . ",
                    "Str Grk": 3588.0,
                    "lemma": "\u03c4\u03bf\u1fe6",
                    "xlit": "tou"
                },
                {
                    "BSB Version": " . . . ",
                    "Str Grk": 2411.0,
                    "lemma": "\u1f31\u03b5\u03c1\u03bf\u1fe6",
                    "xlit": "hierou"
                },
                {
                    "BSB Version": " and ",
                    "Str Grk": 2532.0,
                    "lemma": "\u03ba\u03b1\u1f76",
                    "xlit": "kai"
                },
                {
                    "BSB Version": " elders ",
                    "Str Grk": 4245.0,
                    "lemma": "\u03c0\u03c1\u03b5\u03c3\u03b2\u03c5\u03c4\u03ad\u03c1\u03bf\u03c5\u03c2",
                    "xlit": "presbyterous"
                },
                {
                    "BSB Version": " who ",
                    "Str Grk": 3588.0,
                    "lemma": "\u03c4\u03bf\u1f7a\u03c2",
                    "xlit": "tous"
                },
                {
                    "BSB Version": " had come ",
                    "Str Grk": 3854.0,
                    "lemma": "\u03c0\u03b1\u03c1\u03b1\u03b3\u03b5\u03bd\u03bf\u03bc\u03ad\u03bd\u03bf\u03c5\u03c2",
                    "xlit": "paragenomenous"
                },
                {
                    "BSB Version": " for ",
                    "Str Grk": 1909.0,
                    "lemma": "\u1f10\u03c0\u2019",
                    "xlit": "ep\u2019"
                },
                {
                    "BSB Version": " Him ",
                    "Str Grk": 846.0,
                    "lemma": "\u03b1\u1f50\u03c4\u1f78\u03bd",
                    "xlit": "auton"
                },
                {
                    "BSB Version": " Have you come out ",
                    "Str Grk": 1831.0,
                    "lemma": "\u1f10\u03be\u03ae\u03bb\u03b8\u03b1\u03c4\u03b5",
                    "xlit": "ex\u0113lthate"
                },
                {
                    "BSB Version": " with ",
                    "Str Grk": 3326.0,
                    "lemma": "\u03bc\u03b5\u03c4\u1f70",
                    "xlit": "meta"
                },
                {
                    "BSB Version": " swords ",
                    "Str Grk": 3162.0,
                    "lemma": "\u03bc\u03b1\u03c7\u03b1\u03b9\u03c1\u1ff6\u03bd",
                    "xlit": "machair\u014dn"
                },
                {
                    "BSB Version": " and ",
                    "Str Grk": 2532.0,
                    "lemma": "\u03ba\u03b1\u1f76",
                    "xlit": "kai"
                },
                {
                    "BSB Version": " clubs ",
                    "Str Grk": 3586.0,
                    "lemma": "\u03be\u03cd\u03bb\u03c9\u03bd",
                    "xlit": "xyl\u014dn"
                },
                {
                    "BSB Version": " as ",
                    "Str Grk": 5613.0,
                    "lemma": "\u1f69\u03c2",
                    "xlit": "H\u014ds"
                },
                {
                    "BSB Version": " [you would] against ",
                    "Str Grk": 1909.0,
                    "lemma": "\u1f10\u03c0\u1f76",
                    "xlit": "epi"
                },
                {
                    "BSB Version": " an outlaw ",
                    "Str Grk": 3027.0,
                    "lemma": "\u03bb\u1fc3\u03c3\u03c4\u1f74\u03bd",
                    "xlit": "l\u0113st\u0113n"
                }
            ],
            "verse_text": "And Jesus said to those having come out against Him, <i>the</i> chief priests, and captains of the temple and elders, \"Have you come out with swords and clubs as against a robber?"
        },
        {
            "verse_no": 27520,
            "verse_ref": "Acts 16:36",
            "verse_data": [
                {
                    "BSB Version": " - ",
                    "Str Grk": 1161.0,
                    "lemma": "\u03b4\u1f72",
                    "xlit": "de"
                },
                {
                    "BSB Version": " The ",
                    "Str Grk": 3588.0,
                    "lemma": "\u1f41",
                    "xlit": "ho"
                },
                {
                    "BSB Version": " jailer ",
                    "Str Grk": 1200.0,
                    "lemma": "\u03b4\u03b5\u03c3\u03bc\u03bf\u03c6\u03cd\u03bb\u03b1\u03be",
                    "xlit": "desmophylax"
                },
                {
                    "BSB Version": " informed ",
                    "Str Grk": 518.0,
                    "lemma": "\u1f08\u03c0\u03ae\u03b3\u03b3\u03b5\u03b9\u03bb\u03b5\u03bd",
                    "xlit": "Ap\u0113ngeilen"
                },
                {
                    "BSB Version": " . . . ",
                    "Str Grk": 3778.0,
                    "lemma": "\u03c4\u03bf\u03cd\u03c4\u03bf\u03c5\u03c2",
                    "xlit": "toutous"
                },
                {
                    "BSB Version": " . . . ",
                    "Str Grk": 3588.0,
                    "lemma": "\u03c4\u03bf\u1f7a\u03c2",
                    "xlit": "tous"
                },
                {
                    "BSB Version": " . . . ",
                    "Str Grk": 3056.0,
                    "lemma": "\u03bb\u03cc\u03b3\u03bf\u03c5\u03c2",
                    "xlit": "logous"
                },
                {
                    "BSB Version": " . . . ",
                    "Str Grk": 4314.0,
                    "lemma": "\u03c0\u03c1\u1f78\u03c2",
                    "xlit": "pros"
                },
                {
                    "BSB Version": " - ",
                    "Str Grk": 3588.0,
                    "lemma": "\u03c4\u1f78\u03bd",
                    "xlit": "ton"
                },
                {
                    "BSB Version": " Paul ",
                    "Str Grk": 3972.0,
                    "lemma": "\u03a0\u03b1\u1fe6\u03bb\u03bf\u03bd",
                    "xlit": "Paulon"
                },
                {
                    "BSB Version": " - ",
                    "Str Grk": 3754.0,
                    "lemma": "\u1f45\u03c4\u03b9",
                    "xlit": "hoti"
                },
                {
                    "BSB Version": " The ",
                    "Str Grk": 3588.0,
                    "lemma": "\u03bf\u1f31",
                    "xlit": "hoi"
                },
                {
                    "BSB Version": " magistrates ",
                    "Str Grk": 4755.0,
                    "lemma": "\u03c3\u03c4\u03c1\u03b1\u03c4\u03b7\u03b3\u03bf\u1f76",
                    "xlit": "strat\u0113goi"
                },
                {
                    "BSB Version": " have sent orders ",
                    "Str Grk": 649.0,
                    "lemma": "\u1f08\u03c0\u03ad\u03c3\u03c4\u03b1\u03bb\u03ba\u03b1\u03bd",
                    "xlit": "Apestalkan"
                },
                {
                    "BSB Version": " to ",
                    "Str Grk": 2443.0,
                    "lemma": "\u1f35\u03bd\u03b1",
                    "xlit": "hina"
                },
                {
                    "BSB Version": " release you ",
                    "Str Grk": 630.0,
                    "lemma": "\u1f00\u03c0\u03bf\u03bb\u03c5\u03b8\u1fc6\u03c4\u03b5",
                    "xlit": "apolyth\u0113te"
                },
                {
                    "BSB Version": " - ",
                    "Str Grk": 3767.0,
                    "lemma": "\u03bf\u1f56\u03bd",
                    "xlit": "oun"
                },
                {
                    "BSB Version": " Now ",
                    "Str Grk": 3568.0,
                    "lemma": "\u03bd\u1fe6\u03bd",
                    "xlit": "nyn"
                },
                {
                    "BSB Version": " vvv ",
                    "Str Grk": 1831.0,
                    "lemma": "\u1f10\u03be\u03b5\u03bb\u03b8\u03cc\u03bd\u03c4\u03b5\u03c2",
                    "xlit": "exelthontes"
                },
                {
                    "BSB Version": " you may go on your way ",
                    "Str Grk": 4198.0,
                    "lemma": "\u03c0\u03bf\u03c1\u03b5\u03cd\u03b5\u03c3\u03b8\u03b5",
                    "xlit": "poreuesthe"
                },
                {
                    "BSB Version": " in ",
                    "Str Grk": 1722.0,
                    "lemma": "\u1f10\u03bd",
                    "xlit": "en"
                },
                {
                    "BSB Version": " peace ",
                    "Str Grk": 1515.0,
                    "lemma": "\u03b5\u1f30\u03c1\u03ae\u03bd\u1fc3",
                    "xlit": "eir\u0113n\u0113"
                }
            ],
            "verse_text": "And the jailer reported these words to Paul: \"The captains have sent that you may be let go. Now therefore having gone out, depart in peace.\""
        },
        {
            "verse_no": 27519,
            "verse_ref": "Acts 16:35",
            "verse_data": [
                {
                    "BSB Version": " [When] ",
                    "Str Grk": 1161.0,
                    "lemma": "\u03b4\u1f72",
                    "xlit": "de"
                },
                {
                    "BSB Version": " daylight ",
                    "Str Grk": 2250.0,
                    "lemma": "\u1f29\u03bc\u03ad\u03c1\u03b1\u03c2",
                    "xlit": "H\u0113meras"
                },
                {
                    "BSB Version": " came ",
                    "Str Grk": 1096.0,
                    "lemma": "\u03b3\u03b5\u03bd\u03bf\u03bc\u03ad\u03bd\u03b7\u03c2",
                    "xlit": "genomen\u0113s"
                },
                {
                    "BSB Version": " the ",
                    "Str Grk": 3588.0,
                    "lemma": "\u03bf\u1f31",
                    "xlit": "hoi"
                },
                {
                    "BSB Version": " magistrates ",
                    "Str Grk": 4755.0,
                    "lemma": "\u03c3\u03c4\u03c1\u03b1\u03c4\u03b7\u03b3\u03bf\u1f76",
                    "xlit": "strat\u0113goi"
                },
                {
                    "BSB Version": " sent ",
                    "Str Grk": 649.0,
                    "lemma": "\u1f00\u03c0\u03ad\u03c3\u03c4\u03b5\u03b9\u03bb\u03b1\u03bd",
                    "xlit": "apesteilan"
                },
                {
                    "BSB Version": " [their] ",
                    "Str Grk": 3588.0,
                    "lemma": "\u03c4\u03bf\u1f7a\u03c2",
                    "xlit": "tous"
                },
                {
                    "BSB Version": " officers ",
                    "Str Grk": 4465.0,
                    "lemma": "\u1fe5\u03b1\u03b2\u03b4\u03bf\u03cd\u03c7\u03bf\u03c5\u03c2",
                    "xlit": "rhabdouchous"
                },
                {
                    "BSB Version": " with the order ",
                    "Str Grk": 3004.0,
                    "lemma": "\u03bb\u03ad\u03b3\u03bf\u03bd\u03c4\u03b5\u03c2",
                    "xlit": "legontes"
                },
                {
                    "BSB Version": " Release ",
                    "Str Grk": 630.0,
                    "lemma": "\u1f08\u03c0\u03cc\u03bb\u03c5\u03c3\u03bf\u03bd",
                    "xlit": "Apolyson"
                },
                {
                    "BSB Version": " those ",
                    "Str Grk": 1565.0,
                    "lemma": "\u1f10\u03ba\u03b5\u03af\u03bd\u03bf\u03c5\u03c2",
                    "xlit": "ekeinous"
                },
                {
                    "BSB Version": " - ",
                    "Str Grk": 3588.0,
                    "lemma": "\u03c4\u03bf\u1f7a\u03c2",
                    "xlit": "tous"
                },
                {
                    "BSB Version": " men ",
                    "Str Grk": 444.0,
                    "lemma": "\u1f00\u03bd\u03b8\u03c1\u03ce\u03c0\u03bf\u03c5\u03c2",
                    "xlit": "anthr\u014dpous"
                }
            ],
            "verse_text": "And day having come, the magistrates sent the officers, saying, \"Release those men.\""
        }
    ],
    "other_words": [
        {
            "number": 2186,
            "lemma": "\u1f10\u03c6\u1f77\u03c3\u03c4\u03b7\u03bc\u03b9",
            "xlit": "eph\u00edst\u0113mi",
            "pronunciation": "ef-is'-tay-mee",
            "description": " to stand upon, i.e. be present (in various\n applications, friendly or otherwise, usually literal); ",
            "kjv_def": "--assault, come\n (in, to, unto, upon), be at hand (instant), present, stand (before,\n by, over).",
            "pspeech": "V-AIA-3S"
        },
        {
            "number": 2424,
            "lemma": "\u1f38\u03b7\u03c3\u03bf\u1fe6\u03c2",
            "xlit": "I\u0113so\u00fbs",
            "pronunciation": "ee-ay-sooce'",
            "description": " Jesus (i.e. Jehoshua), the name of our Lord\n and two (three) other Israelites",
            "kjv_def": "Jesus.",
            "pspeech": "N-GMS"
        },
        {
            "number": 3568,
            "lemma": "\u03bd\u1fe6\u03bd",
            "xlit": "n\u0177n",
            "pronunciation": "noon",
            "description": " \"now\" (as adverb of date, a\n transition or emphasis); also as noun or adjective present or\n immediate",
            "kjv_def": "henceforth, + hereafter, of late, soon, present, this\n (time).",
            "pspeech": "Adv"
        },
        {
            "number": 3004,
            "lemma": "\u03bb\u1f73\u03b3\u03c9",
            "xlit": "l\u00e9g\u014d",
            "pronunciation": "leg'-o",
            "description": " properly, to \"lay\" forth, i.e. (figuratively) relate\n (in words (usually of systematic or set discourse; whereas ",
            "kjv_def": "ask,\n bid, boast, call, describe, give out, name, put forth, say(-ing, on),\n shew, speak, tell, utter.",
            "pspeech": "V-PPM/P-NMS"
        }
    ]
}