{
    "wotd": {
        "number": 3837,
        "lemma": "\u03c0\u03b1\u03bd\u03c4\u03b1\u03c7\u03bf\u1fe6",
        "xlit": "pantacho\u00fb",
        "pronunciation": "pan-takh-oo'",
        "kjv_def": "in all places, everywhere.",
        "pspeech": "Adv",
        "description": " universally"
    },
    "verses": [
        {
            "verse_no": 28451,
            "verse_ref": "1 Corinthians 4:17",
            "verse_data": [
                {
                    "BSB Version": " That is why ",
                    "Str Grk": 1223.0,
                    "lemma": "\u0394\u03b9\u1f70",
                    "xlit": "Dia"
                },
                {
                    "BSB Version": " . . . ",
                    "Str Grk": 3778.0,
                    "lemma": "\u03c4\u03bf\u1fe6\u03c4\u03bf",
                    "xlit": "touto"
                },
                {
                    "BSB Version": " . . . ",
                    "Str Grk": 846.0,
                    "lemma": "\u03b1\u1f50\u03c4\u1f78",
                    "xlit": "auto"
                },
                {
                    "BSB Version": " I have sent ",
                    "Str Grk": 3992.0,
                    "lemma": "\u1f14\u03c0\u03b5\u03bc\u03c8\u03b1",
                    "xlit": "epempsa"
                },
                {
                    "BSB Version": " you ",
                    "Str Grk": 4771.0,
                    "lemma": "\u1f51\u03bc\u1fd6\u03bd",
                    "xlit": "hymin"
                },
                {
                    "BSB Version": " Timothy ",
                    "Str Grk": 5095.0,
                    "lemma": "\u03a4\u03b9\u03bc\u03cc\u03b8\u03b5\u03bf\u03bd",
                    "xlit": "Timotheon"
                },
                {
                    "BSB Version": " - ",
                    "Str Grk": 3739.0,
                    "lemma": "\u1f45\u03c2",
                    "xlit": "hos"
                },
                {
                    "BSB Version": " - ",
                    "Str Grk": 1510.0,
                    "lemma": "\u1f10\u03c3\u03c4\u03af\u03bd",
                    "xlit": "estin"
                },
                {
                    "BSB Version": " my ",
                    "Str Grk": 1473.0,
                    "lemma": "\u03bc\u03bf\u03c5",
                    "xlit": "mou"
                },
                {
                    "BSB Version": " beloved ",
                    "Str Grk": 27.0,
                    "lemma": "\u1f00\u03b3\u03b1\u03c0\u03b7\u03c4\u1f78\u03bd",
                    "xlit": "agap\u0113ton"
                },
                {
                    "BSB Version": " and ",
                    "Str Grk": 2532.0,
                    "lemma": "\u03ba\u03b1\u1f76",
                    "xlit": "kai"
                },
                {
                    "BSB Version": " faithful ",
                    "Str Grk": 4103.0,
                    "lemma": "\u03c0\u03b9\u03c3\u03c4\u1f78\u03bd",
                    "xlit": "piston"
                },
                {
                    "BSB Version": " child ",
                    "Str Grk": 5043.0,
                    "lemma": "\u03c4\u03ad\u03ba\u03bd\u03bf\u03bd",
                    "xlit": "teknon"
                },
                {
                    "BSB Version": " in ",
                    "Str Grk": 1722.0,
                    "lemma": "\u1f10\u03bd",
                    "xlit": "en"
                },
                {
                    "BSB Version": " [the] Lord ",
                    "Str Grk": 2962.0,
                    "lemma": "\u039a\u03c5\u03c1\u03af\u1ff3",
                    "xlit": "Kyri\u014d"
                },
                {
                    "BSB Version": " [He] ",
                    "Str Grk": 3739.0,
                    "lemma": "\u1f43\u03c2",
                    "xlit": "hos"
                },
                {
                    "BSB Version": " will remind ",
                    "Str Grk": 363.0,
                    "lemma": "\u1f00\u03bd\u03b1\u03bc\u03bd\u03ae\u03c3\u03b5\u03b9",
                    "xlit": "anamn\u0113sei"
                },
                {
                    "BSB Version": " you ",
                    "Str Grk": 4771.0,
                    "lemma": "\u1f51\u03bc\u1fb6\u03c2",
                    "xlit": "hymas"
                },
                {
                    "BSB Version": " of my ",
                    "Str Grk": 1473.0,
                    "lemma": "\u03bc\u03bf\u03c5",
                    "xlit": "mou"
                },
                {
                    "BSB Version": " - ",
                    "Str Grk": 3588.0,
                    "lemma": "\u03c4\u1f70\u03c2",
                    "xlit": "tas"
                },
                {
                    "BSB Version": " way of life ",
                    "Str Grk": 3598.0,
                    "lemma": "\u1f41\u03b4\u03bf\u03cd\u03c2",
                    "xlit": "hodous"
                },
                {
                    "BSB Version": " - ",
                    "Str Grk": 3588.0,
                    "lemma": "\u03c4\u1f70\u03c2",
                    "xlit": "tas"
                },
                {
                    "BSB Version": " in ",
                    "Str Grk": 1722.0,
                    "lemma": "\u1f10\u03bd",
                    "xlit": "en"
                },
                {
                    "BSB Version": " Christ ",
                    "Str Grk": 5547.0,
                    "lemma": "\u03a7\u03c1\u03b9\u03c3\u03c4\u1ff7",
                    "xlit": "Christ\u014d"
                },
                {
                    "BSB Version": " Jesus ",
                    "Str Grk": 2424.0,
                    "lemma": "\u1f38\u03b7\u03c3\u03bf\u1fe6",
                    "xlit": "I\u0113sou"
                },
                {
                    "BSB Version": " which is exactly what ",
                    "Str Grk": 2531.0,
                    "lemma": "\u03ba\u03b1\u03b8\u1f7c\u03c2",
                    "xlit": "kath\u014ds"
                },
                {
                    "BSB Version": " I teach ",
                    "Str Grk": 1321.0,
                    "lemma": "\u03b4\u03b9\u03b4\u03ac\u03c3\u03ba\u03c9",
                    "xlit": "didask\u014d"
                },
                {
                    "BSB Version": " everywhere ",
                    "Str Grk": 3837.0,
                    "lemma": "\u03c0\u03b1\u03bd\u03c4\u03b1\u03c7\u03bf\u1fe6",
                    "xlit": "pantachou"
                },
                {
                    "BSB Version": " in ",
                    "Str Grk": 1722.0,
                    "lemma": "\u1f10\u03bd",
                    "xlit": "en"
                },
                {
                    "BSB Version": " every ",
                    "Str Grk": 3956.0,
                    "lemma": "\u03c0\u03ac\u03c3\u1fc3",
                    "xlit": "pas\u0113"
                },
                {
                    "BSB Version": " church ",
                    "Str Grk": 1577.0,
                    "lemma": "\u1f10\u03ba\u03ba\u03bb\u03b7\u03c3\u03af\u1fb3",
                    "xlit": "ekkl\u0113sia"
                }
            ],
            "verse_text": "On account of this I sent to you Timothy, who is my beloved and faithful child in <i>the</i> Lord, who will remind of you my ways that <i>are</i> in Christ Jesus, as I teach everywhere in every church."
        },
        {
            "verse_no": 27693,
            "verse_ref": "Acts 21:28",
            "verse_data": [
                {
                    "BSB Version": " crying out ",
                    "Str Grk": 2896.0,
                    "lemma": "\u03ba\u03c1\u03ac\u03b6\u03bf\u03bd\u03c4\u03b5\u03c2",
                    "xlit": "krazontes"
                },
                {
                    "BSB Version": " Men ",
                    "Str Grk": 435.0,
                    "lemma": "\u1f0c\u03bd\u03b4\u03c1\u03b5\u03c2",
                    "xlit": "Andres"
                },
                {
                    "BSB Version": " [of] Israel ",
                    "Str Grk": 2475.0,
                    "lemma": "\u1f38\u03c3\u03c1\u03b1\u03b7\u03bb\u1fd6\u03c4\u03b1\u03b9",
                    "xlit": "Isra\u0113litai"
                },
                {
                    "BSB Version": " help us ",
                    "Str Grk": 997.0,
                    "lemma": "\u03b2\u03bf\u03b7\u03b8\u03b5\u1fd6\u03c4\u03b5",
                    "xlit": "bo\u0113theite"
                },
                {
                    "BSB Version": " This ",
                    "Str Grk": 3778.0,
                    "lemma": "\u03bf\u1f57\u03c4\u03cc\u03c2",
                    "xlit": "houtos"
                },
                {
                    "BSB Version": " is ",
                    "Str Grk": 1510.0,
                    "lemma": "\u1f10\u03c3\u03c4\u03b9\u03bd",
                    "xlit": "estin"
                },
                {
                    "BSB Version": " the ",
                    "Str Grk": 3588.0,
                    "lemma": "\u1f41",
                    "xlit": "ho"
                },
                {
                    "BSB Version": " man ",
                    "Str Grk": 444.0,
                    "lemma": "\u1f04\u03bd\u03b8\u03c1\u03c9\u03c0\u03bf\u03c2",
                    "xlit": "anthr\u014dpos"
                },
                {
                    "BSB Version": " who ",
                    "Str Grk": 3588.0,
                    "lemma": "\u1f41",
                    "xlit": "ho"
                },
                {
                    "BSB Version": " teaches ",
                    "Str Grk": 1321.0,
                    "lemma": "\u03b4\u03b9\u03b4\u03ac\u03c3\u03ba\u03c9\u03bd",
                    "xlit": "didask\u014dn"
                },
                {
                    "BSB Version": " everyone ",
                    "Str Grk": 3956.0,
                    "lemma": "\u03c0\u03ac\u03bd\u03c4\u03b1\u03c2",
                    "xlit": "pantas"
                },
                {
                    "BSB Version": " everywhere ",
                    "Str Grk": 3837.0,
                    "lemma": "\u03c0\u03b1\u03bd\u03c4\u03b1\u03c7\u1fc7",
                    "xlit": "pantach\u0113"
                },
                {
                    "BSB Version": " against ",
                    "Str Grk": 2596.0,
                    "lemma": "\u03ba\u03b1\u03c4\u1f70",
                    "xlit": "kata"
                },
                {
                    "BSB Version": " [our] ",
                    "Str Grk": 3588.0,
                    "lemma": "\u03c4\u03bf\u1fe6",
                    "xlit": "tou"
                },
                {
                    "BSB Version": " people ",
                    "Str Grk": 2992.0,
                    "lemma": "\u03bb\u03b1\u03bf\u1fe6",
                    "xlit": "laou"
                },
                {
                    "BSB Version": " and ",
                    "Str Grk": 2532.0,
                    "lemma": "\u03ba\u03b1\u1f76",
                    "xlit": "kai"
                },
                {
                    "BSB Version": " [against our] ",
                    "Str Grk": 3588.0,
                    "lemma": "\u03c4\u03bf\u1fe6",
                    "xlit": "tou"
                },
                {
                    "BSB Version": " law ",
                    "Str Grk": 3551.0,
                    "lemma": "\u03bd\u03cc\u03bc\u03bf\u03c5",
                    "xlit": "nomou"
                },
                {
                    "BSB Version": " and ",
                    "Str Grk": 2532.0,
                    "lemma": "\u03ba\u03b1\u1f76",
                    "xlit": "kai"
                },
                {
                    "BSB Version": " [against] this ",
                    "Str Grk": 3778.0,
                    "lemma": "\u03c4\u03bf\u03cd\u03c4\u03bf\u03c5",
                    "xlit": "toutou"
                },
                {
                    "BSB Version": " - ",
                    "Str Grk": 3588.0,
                    "lemma": "\u03c4\u03bf\u1fe6",
                    "xlit": "tou"
                },
                {
                    "BSB Version": " place ",
                    "Str Grk": 5117.0,
                    "lemma": "\u03c4\u03cc\u03c0\u03bf\u03c5",
                    "xlit": "topou"
                },
                {
                    "BSB Version": " Furthermore ",
                    "Str Grk": 5037.0,
                    "lemma": "\u03c4\u03b5",
                    "xlit": "te"
                },
                {
                    "BSB Version": " . . . ",
                    "Str Grk": 2089.0,
                    "lemma": "\u1f14\u03c4\u03b9",
                    "xlit": "eti"
                },
                {
                    "BSB Version": " . . . ",
                    "Str Grk": 2532.0,
                    "lemma": "\u03ba\u03b1\u1f76",
                    "xlit": "kai"
                },
                {
                    "BSB Version": " he has brought ",
                    "Str Grk": 1521.0,
                    "lemma": "\u03b5\u1f30\u03c3\u03ae\u03b3\u03b1\u03b3\u03b5\u03bd",
                    "xlit": "eis\u0113gagen"
                },
                {
                    "BSB Version": " Greeks ",
                    "Str Grk": 1672.0,
                    "lemma": "\u1f1d\u03bb\u03bb\u03b7\u03bd\u03b1\u03c2",
                    "xlit": "Hell\u0113nas"
                },
                {
                    "BSB Version": " into ",
                    "Str Grk": 1519.0,
                    "lemma": "\u03b5\u1f30\u03c2",
                    "xlit": "eis"
                },
                {
                    "BSB Version": " the ",
                    "Str Grk": 3588.0,
                    "lemma": "\u03c4\u1f78",
                    "xlit": "to"
                },
                {
                    "BSB Version": " temple ",
                    "Str Grk": 2411.0,
                    "lemma": "\u1f31\u03b5\u03c1\u1f78\u03bd",
                    "xlit": "hieron"
                },
                {
                    "BSB Version": " and ",
                    "Str Grk": 2532.0,
                    "lemma": "\u03ba\u03b1\u1f76",
                    "xlit": "kai"
                },
                {
                    "BSB Version": " defiled ",
                    "Str Grk": 2840.0,
                    "lemma": "\u03ba\u03b5\u03ba\u03bf\u03af\u03bd\u03c9\u03ba\u03b5\u03bd",
                    "xlit": "kekoin\u014dken"
                },
                {
                    "BSB Version": " this ",
                    "Str Grk": 3778.0,
                    "lemma": "\u03c4\u03bf\u1fe6\u03c4\u03bf\u03bd",
                    "xlit": "touton"
                },
                {
                    "BSB Version": " holy ",
                    "Str Grk": 40.0,
                    "lemma": "\u1f05\u03b3\u03b9\u03bf\u03bd",
                    "xlit": "hagion"
                },
                {
                    "BSB Version": " - ",
                    "Str Grk": 3588.0,
                    "lemma": "\u03c4\u1f78\u03bd",
                    "xlit": "ton"
                },
                {
                    "BSB Version": " place ",
                    "Str Grk": 5117.0,
                    "lemma": "\u03c4\u03cc\u03c0\u03bf\u03bd",
                    "xlit": "topon"
                }
            ],
            "verse_text": "crying out, \"Men, Israelites, help! This is the man teaching all those everywhere against the people and the Law and this place. And besides, he has also brought Greeks into the temple and defiled this holy place.\""
        },
        {
            "verse_no": 24894,
            "verse_ref": "Mark 16:20",
            "verse_data": [
                {
                    "BSB Version": " And ",
                    "Str Grk": 1161.0,
                    "lemma": "\u03b4\u1f72",
                    "xlit": "de"
                },
                {
                    "BSB Version": " they ",
                    "Str Grk": 1565.0,
                    "lemma": "\u1f10\u03ba\u03b5\u1fd6\u03bd\u03bf\u03b9",
                    "xlit": "ekeinoi"
                },
                {
                    "BSB Version": " went out ",
                    "Str Grk": 1831.0,
                    "lemma": "\u1f10\u03be\u03b5\u03bb\u03b8\u03cc\u03bd\u03c4\u03b5\u03c2",
                    "xlit": "exelthontes"
                },
                {
                    "BSB Version": " [and] preached ",
                    "Str Grk": 2784.0,
                    "lemma": "\u1f10\u03ba\u03ae\u03c1\u03c5\u03be\u03b1\u03bd",
                    "xlit": "ek\u0113ryxan"
                },
                {
                    "BSB Version": " everywhere ",
                    "Str Grk": 3837.0,
                    "lemma": "\u03c0\u03b1\u03bd\u03c4\u03b1\u03c7\u03bf\u1fe6",
                    "xlit": "pantachou"
                },
                {
                    "BSB Version": " [and] the ",
                    "Str Grk": 3588.0,
                    "lemma": "\u03c4\u03bf\u1fe6",
                    "xlit": "tou"
                },
                {
                    "BSB Version": " Lord ",
                    "Str Grk": 2962.0,
                    "lemma": "\u039a\u03c5\u03c1\u03af\u03bf\u03c5",
                    "xlit": "Kyriou"
                },
                {
                    "BSB Version": " worked through [them] ",
                    "Str Grk": 4903.0,
                    "lemma": "\u03c3\u03c5\u03bd\u03b5\u03c1\u03b3\u03bf\u1fe6\u03bd\u03c4\u03bf\u03c2",
                    "xlit": "synergountos"
                },
                {
                    "BSB Version": " - ",
                    "Str Grk": 2532.0,
                    "lemma": "\u03ba\u03b1\u1f76",
                    "xlit": "kai"
                },
                {
                    "BSB Version": " confirming ",
                    "Str Grk": 950.0,
                    "lemma": "\u03b2\u03b5\u03b2\u03b1\u03b9\u03bf\u1fe6\u03bd\u03c4\u03bf\u03c2",
                    "xlit": "bebaiountos"
                },
                {
                    "BSB Version": " [His] ",
                    "Str Grk": 3588.0,
                    "lemma": "\u03c4\u1f78\u03bd",
                    "xlit": "ton"
                },
                {
                    "BSB Version": " word ",
                    "Str Grk": 3056.0,
                    "lemma": "\u03bb\u03cc\u03b3\u03bf\u03bd",
                    "xlit": "logon"
                },
                {
                    "BSB Version": " by ",
                    "Str Grk": 1223.0,
                    "lemma": "\u03b4\u03b9\u1f70",
                    "xlit": "dia"
                },
                {
                    "BSB Version": " the ",
                    "Str Grk": 3588.0,
                    "lemma": "\u03c4\u1ff6\u03bd",
                    "xlit": "t\u014dn"
                },
                {
                    "BSB Version": " signs ",
                    "Str Grk": 4592.0,
                    "lemma": "\u03c3\u03b7\u03bc\u03b5\u03af\u03c9\u03bd",
                    "xlit": "s\u0113mei\u014dn"
                },
                {
                    "BSB Version": " that accompanied [it] ",
                    "Str Grk": 1872.0,
                    "lemma": "\u1f10\u03c0\u03b1\u03ba\u03bf\u03bb\u03bf\u03c5\u03b8\u03bf\u03cd\u03bd\u03c4\u03c9\u03bd",
                    "xlit": "epakolouthount\u014dn"
                }
            ],
            "verse_text": "And having gone forth, they preached everywhere, the Lord working with <i>them</i> and confirming the word by the accompanying signs."
        },
        {
            "verse_no": 25308,
            "verse_ref": "Luke 9:6",
            "verse_data": [
                {
                    "BSB Version": " So ",
                    "Str Grk": 1161.0,
                    "lemma": "\u03b4\u1f72",
                    "xlit": "de"
                },
                {
                    "BSB Version": " they set out ",
                    "Str Grk": 1831.0,
                    "lemma": "\u1f18\u03be\u03b5\u03c1\u03c7\u03cc\u03bc\u03b5\u03bd\u03bf\u03b9",
                    "xlit": "Exerchomenoi"
                },
                {
                    "BSB Version": " and went ",
                    "Str Grk": 1330.0,
                    "lemma": "\u03b4\u03b9\u03ae\u03c1\u03c7\u03bf\u03bd\u03c4\u03bf",
                    "xlit": "di\u0113rchonto"
                },
                {
                    "BSB Version": " from ",
                    "Str Grk": 2596.0,
                    "lemma": "\u03ba\u03b1\u03c4\u1f70",
                    "xlit": "kata"
                },
                {
                    "BSB Version": " - ",
                    "Str Grk": 3588.0,
                    "lemma": "\u03c4\u1f70\u03c2",
                    "xlit": "tas"
                },
                {
                    "BSB Version": " village to village ",
                    "Str Grk": 2968.0,
                    "lemma": "\u03ba\u03ce\u03bc\u03b1\u03c2",
                    "xlit": "k\u014dmas"
                },
                {
                    "BSB Version": " preaching the gospel ",
                    "Str Grk": 2097.0,
                    "lemma": "\u03b5\u1f50\u03b1\u03b3\u03b3\u03b5\u03bb\u03b9\u03b6\u03cc\u03bc\u03b5\u03bd\u03bf\u03b9",
                    "xlit": "euangelizomenoi"
                },
                {
                    "BSB Version": " and ",
                    "Str Grk": 2532.0,
                    "lemma": "\u03ba\u03b1\u1f76",
                    "xlit": "kai"
                },
                {
                    "BSB Version": " healing [people] ",
                    "Str Grk": 2323.0,
                    "lemma": "\u03b8\u03b5\u03c1\u03b1\u03c0\u03b5\u03cd\u03bf\u03bd\u03c4\u03b5\u03c2",
                    "xlit": "therapeuontes"
                },
                {
                    "BSB Version": " everywhere ",
                    "Str Grk": 3837.0,
                    "lemma": "\u03c0\u03b1\u03bd\u03c4\u03b1\u03c7\u03bf\u1fe6",
                    "xlit": "pantachou"
                }
            ],
            "verse_text": "And going forth, they were passing through the villages, proclaiming the gospel and healing everywhere."
        }
    ],
    "other_words": [
        {
            "number": 1577,
            "lemma": "\u1f10\u03ba\u03ba\u03bb\u03b7\u03c3\u1f77\u03b1",
            "xlit": "ekkl\u0113s\u00eda",
            "pronunciation": "ek-klay-see'-ah",
            "kjv_def": "assembly, church.",
            "pspeech": "N-AFS",
            "description": " a calling out, i.e. (concretely) a popular meeting, especially a religious congregation (Jewish synagogue, or Christian community of members on earth or saints in heaven or both)"
        },
        {
            "number": 3551,
            "lemma": "\u03bd\u1f79\u03bc\u03bf\u03c2",
            "xlit": "n\u00f3mos",
            "pronunciation": "nom'-os",
            "kjv_def": "law.",
            "pspeech": "N-AMS",
            "description": " law (through the idea of prescriptive usage), genitive case (regulation), specially, (of Moses (including the volume); also of the Gospel), or figuratively (a principle)"
        },
        {
            "number": 3056,
            "lemma": "\u03bb\u1f79\u03b3\u03bf\u03c2",
            "xlit": "l\u00f3gos",
            "pronunciation": "log'-os",
            "kjv_def": "account, cause,\n communication, X concerning, doctrine, fame, X have to do, intent,\n matter, mouth, preaching, question, reason, + reckon, remove,\n say(-ing), shew, X speaker, speech, talk, thing, + none of these\n things move me, tidings, treatise, utterance, word, work.",
            "pspeech": "N-GMS",
            "description": " something said (including the thought); by implication, a topic (subject of discourse), also reasoning (the mental faculty) or motive; by extension, a computation; specially, (with the article in John) the Divine Expression (i.e. Christ)"
        },
        {
            "number": 2323,
            "lemma": "\u03b8\u03b5\u03c1\u03b1\u03c0\u03b5\u1f7b\u03c9",
            "xlit": "therape\u00fa\u014d",
            "pronunciation": "ther-ap-yoo'-o",
            "kjv_def": "cure, heal,\n worship.",
            "pspeech": "V-PPA-NMS",
            "description": " to wait upon menially, i.e. (figuratively) to adore (God), or (specially) to relieve (of disease)"
        }
    ]
}